prompt_cheater/__init__.py
prompt_cheater/ai.py
prompt_cheater/config.py
prompt_cheater/main.py
prompt_cheater/tmux.py
prompt_cheater/ui.py
prompt_cheater-0.2.2.dist-info/METADATA
prompt_cheater-0.2.2.dist-info/WHEEL
prompt_cheater-0.2.2.dist-info/entry_points.txt
prompt_cheater-0.2.2.dist-info/licenses/LICENSE
prompt_cheater-0.2.2.dist-info/RECORD
