Metadata-Version: 2.4
Name: prompt-cheater
Version: 0.2.2
Summary: Convert natural language to Claude-friendly XML prompts and inject into Tmux
License: MIT
License-File: LICENSE
Keywords: claude,ai,prompt,tmux,cli,xml,gemini
Author: Kim Gyudong
Requires-Python: >=3.10,<4.0
Classifier: Development Status :: 4 - Beta
Classifier: Environment :: Console
Classifier: Intended Audience :: Developers
Classifier: License :: OSI Approved :: MIT License
Classifier: Operating System :: MacOS
Classifier: Operating System :: POSIX :: Linux
Classifier: Programming Language :: Python :: 3
Classifier: Programming Language :: Python :: 3.10
Classifier: Programming Language :: Python :: 3.11
Classifier: Programming Language :: Python :: 3.12
Classifier: Programming Language :: Python :: 3.13
Classifier: Programming Language :: Python :: 3.14
Classifier: Topic :: Software Development :: Libraries :: Python Modules
Requires-Dist: google-genai (>=1.0.0,<2.0.0)
Requires-Dist: libtmux (>=0.37.0,<0.38.0)
Requires-Dist: prompt-toolkit (>=3.0.0,<4.0.0)
Requires-Dist: python-dotenv (>=1.0.0,<2.0.0)
Requires-Dist: rich (>=13.7.0,<14.0.0)
Requires-Dist: typer (>=0.12.0,<0.13.0)
Project-URL: Documentation, https://github.com/KIMGYUDONG/prompt-cheater#readme
Project-URL: Homepage, https://github.com/KIMGYUDONG/prompt-cheater
Project-URL: Repository, https://github.com/KIMGYUDONG/prompt-cheater
